papyrus/__init__.py
sphinx_papyrus_theme-0.0.1.dev0.dist-info/LICENSE
sphinx_papyrus_theme-0.0.1.dev0.dist-info/METADATA
sphinx_papyrus_theme-0.0.1.dev0.dist-info/WHEEL
sphinx_papyrus_theme-0.0.1.dev0.dist-info/entry_points.txt
sphinx_papyrus_theme-0.0.1.dev0.dist-info/top_level.txt
sphinx_papyrus_theme-0.0.1.dev0.dist-info/RECORD
